django_foundation_statics-5.4.7.post2.dist-info/DESCRIPTION.rst
django_foundation_statics-5.4.7.post2.dist-info/METADATA
django_foundation_statics-5.4.7.post2.dist-info/RECORD
django_foundation_statics-5.4.7.post2.dist-info/WHEEL
django_foundation_statics-5.4.7.post2.dist-info/metadata.json
django_foundation_statics-5.4.7.post2.dist-info/top_level.txt
foundation/__init__.py
foundation/models.py
foundation/static/css/foundation.css
foundation/static/css/foundation.min.css
foundation/static/css/normalize.css
foundation/static/js/foundation.min.js
foundation/static/js/foundation/foundation.abide.js
foundation/static/js/foundation/foundation.accordion.js
foundation/static/js/foundation/foundation.alert.js
foundation/static/js/foundation/foundation.clearing.js
foundation/static/js/foundation/foundation.dropdown.js
foundation/static/js/foundation/foundation.equalizer.js
foundation/static/js/foundation/foundation.interchange.js
foundation/static/js/foundation/foundation.joyride.js
foundation/static/js/foundation/foundation.js
foundation/static/js/foundation/foundation.magellan.js
foundation/static/js/foundation/foundation.offcanvas.js
foundation/static/js/foundation/foundation.orbit.js
foundation/static/js/foundation/foundation.reveal.js
foundation/static/js/foundation/foundation.slider.js
foundation/static/js/foundation/foundation.tab.js
foundation/static/js/foundation/foundation.tooltip.js
foundation/static/js/foundation/foundation.topbar.js
foundation/static/js/vendor/fastclick.js
foundation/static/js/vendor/jquery.cookie.js
foundation/static/js/vendor/jquery.js
foundation/static/js/vendor/modernizr.js
foundation/static/js/vendor/placeholder.js
foundation_scss/__init__.py
foundation_scss/models.py
foundation_scss/static/js/foundation.min.js
foundation_scss/static/js/foundation/foundation.abide.js
foundation_scss/static/js/foundation/foundation.accordion.js
foundation_scss/static/js/foundation/foundation.alert.js
foundation_scss/static/js/foundation/foundation.clearing.js
foundation_scss/static/js/foundation/foundation.dropdown.js
foundation_scss/static/js/foundation/foundation.equalizer.js
foundation_scss/static/js/foundation/foundation.interchange.js
foundation_scss/static/js/foundation/foundation.joyride.js
foundation_scss/static/js/foundation/foundation.js
