Metadata-Version: 2.0
Name: django-foundation-statics
Version: 5.4.7.post2
Summary: Zurb Foundation (http://foundation.zurb.com) static files packaged in a django app to speed up new applications and deployment.
Home-page: https://github.com/benbacardi/django-foundation-statics
Author: Ben Cardy
Author-email: benbacardi@gmail.com
License: MIT
Keywords: django,zurb,foundation,staticfiles
Platform: any
Classifier: Development Status :: 5 - Production/Stable
Classifier: Environment :: Web Environment
Classifier: Framework :: Django
Classifier: Intended Audience :: Developers
Classifier: Natural Language :: English
Classifier: License :: OSI Approved :: MIT License
Classifier: Operating System :: OS Independent
Classifier: Programming Language :: Python
Classifier: Topic :: Utilities
